dtwmetrics/__init__.py
dtwmetrics/dtwmetrics.py
dtwmetrics/dtwutils.py
dtwmetrics/utils.py
dtwmetrics/version.py
dtwmetrics-0.1.2.dist-info/LICENSE
dtwmetrics-0.1.2.dist-info/METADATA
dtwmetrics-0.1.2.dist-info/WHEEL
dtwmetrics-0.1.2.dist-info/RECORD
