Metadata-Version: 2.1
Name: dtwmetrics
Version: 0.1.2
Summary: Dynamic time warping metrics.
License: MIT
Author: danielvogler
Requires-Python: >=3.11.2,<4.0.0
Classifier: License :: OSI Approved :: MIT License
Classifier: Programming Language :: Python :: 3
Classifier: Programming Language :: Python :: 3.12
Requires-Dist: matplotlib (>=3.8.2,<4.0.0)
Requires-Dist: pylint (>=3.0.2,<4.0.0)
Requires-Dist: pytest (>=7.4.3,<8.0.0)
Requires-Dist: scipy (>=1.11.4,<2.0.0)
Requires-Dist: yamllint (>=1.32.0,<2.0.0)
